{"相原雪乃": {"cv": "-", "attribute": "Cu"}, "赤西瑛梨華": {"cv": "-", "attribute": "Cu"}, "浅野風香": {"cv": "-", "attribute": "Cu"}, "安部菜々": {"cv": "三宅麻理恵", "attribute": "Cu"}, "有浦柑奈": {"cv": "-", "attribute": "Cu"}, "安斎都": {"cv": "-", "attribute": "Cu"}, "五十嵐響子": {"cv": "種﨑敦美", "attribute": "Cu"}, "池袋晶葉": {"cv": "-", "attribute": "Cu"}, "一ノ瀬志希": {"cv": "藍原ことみ", "attribute": "Cu"}, "今井加奈": {"cv": "-", "attribute": "Cu"}, "井村雪菜": {"cv": "-", "attribute": "Cu"}, "江上椿": {"cv": "-", "attribute": "Cu"}, "太田優": {"cv": "-", "attribute": "Cu"}, "大西由里子": {"cv": "-", "attribute": "Cu"}, "大沼くるみ": {"cv": "-", "attribute": "Cu"}, "大原みちる": {"cv": "-", "attribute": "Cu"}, "緒方智絵里": {"cv": "大空直美", "attribute": "Cu"}, "奥山沙織": {"cv": "-", "attribute": "Cu"}, "乙倉悠貴": {"cv": "中島由貴", "attribute": "Cu"}, "日下部若葉": {"cv": "-", "attribute": "Cu"}, "工藤忍": {"cv": "-", "attribute": "Cu"}, "クラリス": {"cv": "-", "attribute": "Cu"}, "栗原ネネ": {"cv": "-", "attribute": "Cu"}, "古賀小春": {"cv": "-", "attribute": "Cu"}, "輿水幸子": {"cv": "竹達彩奈", "attribute": "Cu"}, "小早川紗枝": {"cv": "立花理香", "attribute": "Cu"}, "小日向美穂": {"cv": "津田美波", "attribute": "Cu"}, "西園寺琴歌": {"cv": "-", "attribute": "Cu"}, "榊原里美": {"cv": "-", "attribute": "Cu"}, "佐久間まゆ": {"cv": "牧野由依", "attribute": "Cu"}, "櫻井桃華": {"cv": "照井春佳", "attribute": "Cu"}, "椎名法子": {"cv": "都丸ちよ", "attribute": "Cu"}, "島村卯月": {"cv": "大橋彩香", "attribute": "Cu"}, "白菊ほたる": {"cv": "-", "attribute": "Cu"}, "涼宮星花": {"cv": "-", "attribute": "Cu"}, "関裕美": {"cv": "-", "attribute": "Cu"}, "月宮雅": {"cv": "-", "attribute": "Cu"}, "道明寺歌鈴": {"cv": "新田ひより", "attribute": "Cu"}, "長富蓮実": {"cv": "-", "attribute": "Cu"}, "中野有香": {"cv": "下地紫野", "attribute": "Cu"}, "丹羽仁美": {"cv": "-", "attribute": "Cu"}, "早坂美玲": {"cv": "朝井彩加", "attribute": "Cu"}, "原田美世": {"cv": "-", "attribute": "Cu"}, "兵藤レナ": {"cv": "-", "attribute": "Cu"}, "福山舞": {"cv": "-", "attribute": "Cu"}, "藤本里奈": {"cv": "金子真由美", "attribute": "Cu"}, "双葉杏": {"cv": "五十嵐裕美", "attribute": "Cu"}, "前川みく": {"cv": "高森奈津美", "attribute": "Cu"}, "松原早耶": {"cv": "-", "attribute": "Cu"}, "間中美里": {"cv": "-", "attribute": "Cu"}, "水本ゆかり": {"cv": "藤田茜", "attribute": "Cu"}, "三村かな子": {"cv": "大坪由佳", "attribute": "Cu"}, "宮本フレデリカ": {"cv": "髙野麻美", "attribute": "Cu"}, "棟方愛海": {"cv": "-", "attribute": "Cu"}, "村松さくら": {"cv": "-", "attribute": "Cu"}, "持田亜里沙": {"cv": "-", "attribute": "Cu"}, "桃井あずき": {"cv": "-", "attribute": "Cu"}, "楊菲菲": {"cv": "-", "attribute": "Cu"}, "柳清良": {"cv": "-", "attribute": "Cu"}, "柳瀬美由紀": {"cv": "-", "attribute": "Cu"}, "遊佐こずえ": {"cv": "-", "attribute": "Cu"}, "横山千佳": {"cv": "-", "attribute": "Cu"}, "相川千夏": {"cv": "-", "attribute": "Co"}, "浅利七海": {"cv": "-", "attribute": "Co"}, "アナスタシア": {"cv": "上坂すみれ", "attribute": "Co"}, "綾瀬穂乃香": {"cv": "-", "attribute": "Co"}, "荒木比奈": {"cv": "-", "attribute": "Co"}, "伊集院惠": {"cv": "-", "attribute": "Co"}, "氏家むつみ": {"cv": "-", "attribute": "Co"}, "梅木音葉": {"cv": "-", "attribute": "Co"}, "大石泉": {"cv": "-", "attribute": "Co"}, "岡崎泰葉": {"cv": "-", "attribute": "Co"}, "上条春菜": {"cv": "長島光那", "attribute": "Co"}, "神谷奈緒": {"cv": "松井恵理子", "attribute": "Co"}, "川島瑞樹": {"cv": "東山奈央", "attribute": "Co"}, "神崎蘭子": {"cv": "内田真礼", "attribute": "Co"}, "岸部彩華": {"cv": "-", "attribute": "Co"}, "木場真奈美": {"cv": "-", "attribute": "Co"}, "桐野アヤ": {"cv": "-", "attribute": "Co"}, "桐生つかさ": {"cv": "-", "attribute": "Co"}, "黒川千秋": {"cv": "-", "attribute": "Co"}, "ケイト": {"cv": "-", "attribute": "Co"}, "小室千奈美": {"cv": "-", "attribute": "Co"}, "鷺沢文香": {"cv": "M・A・O", "attribute": "Co"}, "佐々木千枝": {"cv": "今井麻夏", "attribute": "Co"}, "佐城雪美": {"cv": "-", "attribute": "Co"}, "塩見周子": {"cv": "ルゥ ティン", "attribute": "Co"}, "篠原礼": {"cv": "-", "attribute": "Co"}, "渋谷凛": {"cv": "福原綾香", "attribute": "Co"}, "白坂小梅": {"cv": "桜咲千依", "attribute": "Co"}, "瀬名詩織": {"cv": "-", "attribute": "Co"}, "高垣楓": {"cv": "早見沙織", "attribute": "Co"}, "高橋礼子": {"cv": "-", "attribute": "Co"}, "鷹富士茄子": {"cv": "-", "attribute": "Co"}, "高峯のあ": {"cv": "-", "attribute": "Co"}, "多田李衣菜": {"cv": "青木瑠璃子", "attribute": "Co"}, "橘ありす": {"cv": "佐藤亜美菜", "attribute": "Co"}, "東郷あい": {"cv": "-", "attribute": "Co"}, "成宮由愛": {"cv": "-", "attribute": "Co"}, "西川保奈美": {"cv": "-", "attribute": "Co"}, "新田美波": {"cv": "洲崎綾", "attribute": "Co"}, "二宮飛鳥": {"cv": "青木志貴", "attribute": "Co"}, "服部瞳子": {"cv": "-", "attribute": "Co"}, "速水奏": {"cv": "飯田友子", "attribute": "Co"}, "柊志乃": {"cv": "-", "attribute": "Co"}, "藤居朋": {"cv": "-", "attribute": "Co"}, "藤原肇": {"cv": "-", "attribute": "Co"}, "古澤頼子": {"cv": "-", "attribute": "Co"}, "ヘレン": {"cv": "-", "attribute": "Co"}, "北条加蓮": {"cv": "渕上舞", "attribute": "Co"}, "松尾千鶴": {"cv": "-", "attribute": "Co"}, "松永涼": {"cv": "千菅春香", "attribute": "Co"}, "松本沙理奈": {"cv": "-", "attribute": "Co"}, "水木聖來": {"cv": "-", "attribute": "Co"}, "水野翠": {"cv": "-", "attribute": "Co"}, "三船美優": {"cv": "原田彩楓", "attribute": "Co"}, "望月聖": {"cv": "-", "attribute": "Co"}, "森久保乃々": {"cv": "高橋花林", "attribute": "Co"}, "八神マキノ": {"cv": "-", "attribute": "Co"}, "大和亜季": {"cv": "村中知", "attribute": "Co"}, "結城晴": {"cv": "-", "attribute": "Co"}, "吉岡沙紀": {"cv": "-", "attribute": "Co"}, "ライラ": {"cv": "-", "attribute": "Co"}, "脇山珠美": {"cv": "嘉山未紗", "attribute": "Co"}, "和久井留美": {"cv": "-", "attribute": "Co"}, "愛野渚": {"cv": "-", "attribute": "Pa"}, "相葉夕美": {"cv": "木村珠莉", "attribute": "Pa"}, "赤城みりあ": {"cv": "黒沢ともよ", "attribute": "Pa"}, "イヴ・サンタクロース": {"cv": "-", "attribute": "Pa"}, "市原仁奈": {"cv": "久野美咲", "attribute": "Pa"}, "上田鈴帆": {"cv": "春野ななみ", "attribute": "Pa"}, "衛藤美紗希": {"cv": "-", "attribute": "Pa"}, "海老原菜帆": {"cv": "-", "attribute": "Pa"}, "及川雫": {"cv": "のぐちゆり", "attribute": "Pa"}, "大槻唯": {"cv": "山下七海", "attribute": "Pa"}, "片桐早苗": {"cv": "和氣あず未", "attribute": "Pa"}, "北川真尋": {"cv": "-", "attribute": "Pa"}, "喜多日菜子": {"cv": "-", "attribute": "Pa"}, "喜多見柚": {"cv": "-", "attribute": "Pa"}, "木村夏樹": {"cv": "安野希世乃", "attribute": "Pa"}, "キャシー・グラハム": {"cv": "-", "attribute": "Pa"}, "小関麗奈": {"cv": "-", "attribute": "Pa"}, "小松伊吹": {"cv": "-", "attribute": "Pa"}, "財前時子": {"cv": "-", "attribute": "Pa"}, "斉藤洋子": {"cv": "-", "attribute": "Pa"}, "冴島清美": {"cv": "-", "attribute": "Pa"}, "佐藤心": {"cv": "花守ゆみり", "attribute": "Pa"}, "沢田麻理菜": {"cv": "-", "attribute": "Pa"}, "首藤葵": {"cv": "-", "attribute": "Pa"}, "城ヶ崎美嘉": {"cv": "佳村はるか", "attribute": "Pa"}, "城ヶ崎莉嘉": {"cv": "山本希望", "attribute": "Pa"}, "杉坂海": {"cv": "-", "attribute": "Pa"}, "仙崎恵磨": {"cv": "-", "attribute": "Pa"}, "相馬夏美": {"cv": "-", "attribute": "Pa"}, "高森藍子": {"cv": "金子有希", "attribute": "Pa"}, "土屋亜子": {"cv": "-", "attribute": "Pa"}, "十時愛梨": {"cv": "原田ひとみ", "attribute": "Pa"}, "ナターリア": {"cv": "-", "attribute": "Pa"}, "並木芽衣子": {"cv": "-", "attribute": "Pa"}, "南条光": {"cv": "-", "attribute": "Pa"}, "難波笑美": {"cv": "伊達朱里紗", "attribute": "Pa"}, "西島櫂": {"cv": "-", "attribute": "Pa"}, "野々村そら": {"cv": "-", "attribute": "Pa"}, "浜川愛結奈": {"cv": "-", "attribute": "Pa"}, "浜口あやめ": {"cv": "田澤茉純", "attribute": "Pa"}, "日野茜": {"cv": "赤﨑千夏*13", "attribute": "Pa"}, "姫川友紀": {"cv": "杜野まこ", "attribute": "Pa"}, "星輝子": {"cv": "松田颯水", "attribute": "Pa"}, "堀裕子": {"cv": "鈴木絵理", "attribute": "Pa"}, "本田未央": {"cv": "原紗友里", "attribute": "Pa"}, "槙原志保": {"cv": "-", "attribute": "Pa"}, "松山久美子": {"cv": "-", "attribute": "Pa"}, "的場梨沙": {"cv": "-", "attribute": "Pa"}, "真鍋いつき": {"cv": "-", "attribute": "Pa"}, "三好紗南": {"cv": "-", "attribute": "Pa"}, "向井拓海": {"cv": "原優子", "attribute": "Pa"}, "村上巴": {"cv": "-", "attribute": "Pa"}, "メアリー・コクラン": {"cv": "-", "attribute": "Pa"}, "諸星きらり": {"cv": "松嵜麗", "attribute": "Pa"}, "矢口美羽": {"cv": "-", "attribute": "Pa"}, "依田芳乃": {"cv": "高田憂希", "attribute": "Pa"}, "龍崎薫": {"cv": "春瀬なつみ", "attribute": "Pa"}, "若林智香": {"cv": "-", "attribute": "Pa"}}